LICENSE
README
bootstrap.py
buildout.cfg
setup.py
src/django_encrypt.egg-info/PKG-INFO
src/django_encrypt.egg-info/SOURCES.txt
src/django_encrypt.egg-info/dependency_links.txt
src/django_encrypt.egg-info/requires.txt
src/django_encrypt.egg-info/top_level.txt
src/encrypt/__init__.py
src/encrypt/models.py
src/encrypt/pyRijndael.py
src/encrypt/testsettings.py
src/encrypt/views.py
src/encrypt/tests/__init__.py
src/encrypt/tests/test_models.py
src/encrypt/tests/test_setup.py