Metadata-Version: 1.0
Name: django-encrypt
Version: 0.1
Summary: A quick way to encrypt python objects and store
Home-page: UNKNOWN
Author: Joshua Williams
Author-email: jowillia@gmail.com
License: BSD
Platform: UNKNOWN
Classifier: Development Status :: 4 - Beta
Classifier: Framework :: Django
Classifier: Intended Audience :: Developers
Classifier: License :: OSI Approved :: BSD License
Classifier: Operating System :: OS Independent
Classifier: Programming Language :: Python
Classifier: Topic :: Internet :: WWW/HTTP
